jarvis_prameya_mohanty/__init__.py
jarvis_prameya_mohanty-0.0.1.dist-info/LICENSE
jarvis_prameya_mohanty-0.0.1.dist-info/METADATA
jarvis_prameya_mohanty-0.0.1.dist-info/WHEEL
jarvis_prameya_mohanty-0.0.1.dist-info/top_level.txt
jarvis_prameya_mohanty-0.0.1.dist-info/RECORD
