Metadata-Version: 2.1
Name: jarvis-prameya-mohanty
Version: 0.0.1
Summary: This is a package which can perform amazing tasks.
Home-page: UNKNOWN
Author: Prameya
Author-email: prameyamohanty14@gmail.com
License: UNKNOWN
Platform: UNKNOWN
Classifier: Development Status :: 1 - Planning
Classifier: Intended Audience :: Developers
Classifier: Programming Language :: Python :: 3
Classifier: Operating System :: Microsoft :: Windows
License-File: LICENSE
Requires-Dist: pyttsx3
Requires-Dist: SpeechRecognition
Requires-Dist: wikipedia
